dmv_tool/__init__.py
dmv_tool/cli/__init__.py
dmv_tool/cli/main.py
dmv_tool/configs/__init__.py
dmv_tool/configs/constants.py
dmv_tool/data/__init__.py
dmv_tool/data/validation_data_1.2.json
dmv_tool/data/validation_data_1.3.json
dmv_tool/data/validation_data_1.4.1.json
dmv_tool/data/validation_data_1.4.2.json
dmv_tool/data/validation_data_1.4.json
dmv_tool/data/validation_data_1.5.json
dmv_tool/generators/__init__.py
dmv_tool/generators/conformance.py
dmv_tool/generators/core.py
dmv_tool/generators/datamodel.py
dmv_tool/generators/elements.py
dmv_tool/generators/helpers.py
dmv_tool/generators/main.py
dmv_tool/generators/serializers.py
dmv_tool/generators/xml_parser.py
dmv_tool/parsers/__init__.py
dmv_tool/parsers/constants.py
dmv_tool/parsers/wildcard_logs.py
dmv_tool/utils/__init__.py
dmv_tool/utils/helpers.py
dmv_tool/validators/__init__.py
dmv_tool/validators/conformance_checker.py
dmv_tool/validators/constants.py
dmv_tool/validators/reporting.py
dmv_tool/validators/utils.py
esp_matter_dm_validator-1.0.0.dist-info/METADATA
esp_matter_dm_validator-1.0.0.dist-info/WHEEL
esp_matter_dm_validator-1.0.0.dist-info/entry_points.txt
esp_matter_dm_validator-1.0.0.dist-info/top_level.txt
esp_matter_dm_validator-1.0.0.dist-info/RECORD
